{
  "model": "/home/noah/.cache/pacha/models/f6de13c77f843535.gguf",
  "tier": "smoke",
  "passed": true,
  "gates_executed": 11,
  "gates_skipped": 0,
  "gates_failed": 0,
  "total_duration_ms": 41818,
  "gates": [
    {
      "name": "inspect",
      "display_name": "Inspect",
      "status": "PASS",
      "message": "OK",
      "duration_ms": 1477
    },
    {
      "name": "validate",
      "display_name": "Validate",
      "status": "PASS",
      "message": "OK",
      "duration_ms": 5986
    },
    {
      "name": "validate_quality",
      "display_name": "Validate (quality)",
      "status": "PASS",
      "message": "OK",
      "duration_ms": 6112
    },
    {
      "name": "tensors",
      "display_name": "Tensors",
      "status": "PASS",
      "message": "OK",
      "duration_ms": 1420
    },
    {
      "name": "lint",
      "display_name": "Lint",
      "status": "PASS",
      "message": "OK",
      "duration_ms": 741
    },
    {
      "name": "debug",
      "display_name": "Debug",
      "status": "PASS",
      "message": "OK",
      "duration_ms": 1342
    },
    {
      "name": "tree",
      "display_name": "Tree",
      "status": "PASS",
      "message": "OK",
      "duration_ms": 1379
    },
    {
      "name": "hex",
      "display_name": "Hex",
      "status": "PASS",
      "message": "OK",
      "duration_ms": 772
    },
    {
      "name": "flow",
      "display_name": "Flow",
      "status": "PASS",
      "message": "OK",
      "duration_ms": 2087
    },
    {
      "name": "explain",
      "display_name": "Explain",
      "status": "PASS",
      "message": "OK",
      "duration_ms": 1405
    },
    {
      "name": "check",
      "display_name": "Check (pipeline)",
      "status": "PASS",
      "message": "OK",
      "duration_ms": 19088
    }
  ]
}
